MANIFEST.in
README.md
setup.py
nonce2vec/__init__.py
nonce2vec/main.py
nonce2vec.egg-info/PKG-INFO
nonce2vec.egg-info/SOURCES.txt
nonce2vec.egg-info/dependency_links.txt
nonce2vec.egg-info/entry_points.txt
nonce2vec.egg-info/not-zip-safe
nonce2vec.egg-info/requires.txt
nonce2vec.egg-info/top_level.txt
nonce2vec/exceptions/__init__.py
nonce2vec/exceptions/method.py
nonce2vec/exceptions/parameter.py
nonce2vec/logging/__init__.py
nonce2vec/logging/logging.yml
nonce2vec/models/__init__.py
nonce2vec/models/informativeness.py
nonce2vec/models/nonce2vec.py
nonce2vec/resources/__init__.py
nonce2vec/utils/__init__.py
nonce2vec/utils/config.py
nonce2vec/utils/files.py
nonce2vec/utils/immutables.py