Metadata-Version: 2.1
Name: nonce2vec
Version: 2.0.1
Summary: A python module to generate word embeddings from tiny data
Home-page: https://github.com/minimalparts/nonce2vec
Author:  Alexandre Kabbach and Aurélie Herbelot
Author-email: akb@3azouz.net
License: MIT
Download-URL: https://github.com/minimalparts/nonce2vec/#files
Keywords: word2vec,word-embeddings,incremental-learning
Platform: any
Classifier: Development Status :: 2 - Pre-Alpha
Classifier: Environment :: Web Environment
Classifier: Intended Audience :: Developers
Classifier: Intended Audience :: Education
Classifier: Intended Audience :: Science/Research
Classifier: License :: OSI Approved :: MIT License
Classifier: Natural Language :: English
Classifier: Operating System :: OS Independent
Classifier: Programming Language :: Python :: 3.5
Classifier: Programming Language :: Python :: 3.6
Classifier: Programming Language :: Python :: 3.7
Classifier: Topic :: Scientific/Engineering :: Artificial Intelligence
Classifier: Topic :: Text Processing :: Linguistic
